{
  "trig-tour.title": {
    "value": "Trig Tour"
  },
  "angle": {
    "value": "angle"
  },
  "cos": {
    "value": "cos"
  },
  "degrees": {
    "value": "Degrees"
  },
  "grid": {
    "value": "Grid"
  },
  "labels": {
    "value": "Labels"
  },
  "rads": {
    "value": "rads"
  },
  "radians": {
    "value": "Radians"
  },
  "sin": {
    "value": "sin"
  },
  "specialAngles": {
    "value": "Special Angles"
  },
  "tan": {
    "value": "tan"
  },
  "x": {
    "value": "x"
  },
  "y": {
    "value": "y"
  },
  "values": {
    "value": "Values"
  },
  "vs": {
    "value": "vs"
  },
  "valueUnitPattern": {
    "value": "{0} {1}"
  },
  "numberPiPattern": {
    "value": "{0}{1}"
  },
  "pointOffScale": {
    "value": "Point off screen!"
  },
  "a11y": {
    "graphViewAccordionBox": {
      "tanAccessibleName": {
        "value": "Tangent Theta versus Theta"
      },
      "sinAccessibleName": {
        "value": "Sine Theta versus Theta"
      },
      "cosAccessibleName": {
        "value": "Cosine Theta versus Theta"
      },
      "helpText": {
        "value": "Expand to explore graph of function versus angle."
      }
    },
    "valuesAccordionBox": {
      "helpText": {
        "value": "Expand to show angle measure, coordinates, and trig value."
      }
    },
    "unitsRadioButtons": {
      "accessibleName": {
        "value": "Angle Units"
      }
    },
    "graphRadioButtons": {
      "accessibleName": {
        "value": "Trig Functions"
      },
      "helpText": {
        "value": "Compare values and graphs of different trig functions."
      },
      "cosButton": {
        "accessibleName": {
          "value": "Cosine"
        }
      },
      "sinButton": {
        "accessibleName": {
          "value": "Sine"
        }
      },
      "tanButton": {
        "accessibleName": {
          "value": "Tangent"
        }
      }
    },
    "unitCirclePoint": {
      "accessibleName": {
        "value": "Point on Circle"
      },
      "helpText": {
        "value": "Move point on circle to change angle."
      }
    },
    "graphPoint": {
      "accessibleName": {
        "value": "Point on Graph"
      },
      "helpText": {
        "value": "Move point on graph to change theta."
      }
    },
    "specialAnglesCheckbox": {
      "helpText": {
        "value": "Explore with or without angles constrained to multiples of 30, 45, 60, and 90 degrees."
      }
    },
    "labelsCheckbox": {
      "helpText": {
        "value": "Explore angles with or without help of visual labels on unit circle and graph."
      }
    },
    "gridCheckbox": {
      "helpText": {
        "value": "Create angles with or without help of coordinate grid on unit circle."
      }
    },
    "screenSummary": {
      "playArea": {
        "value": "An interactive circle with a radius of 1 is centered on a coordinate plane. A movable point on the circle defines an angle theta as the point is rotated counterclockwise or clockwise from the x-axis. A right triangle is formed by the radius, a vertical line from the point to the x-axis, and the x-axis. There are options to explore different trigonometric functions and simultaneously highlight sides of the triangle inside the circle. Below the circle, an accordion box can display a graph of the selected function versus theta. The graph has a corresponding movable point which can go off screen."
      },
      "controlArea": {
        "value": "Use labels, background grid, and special angles, as needed, to guide your exploration of trigonometric functions. Reset the sim to start over."
      },
      "details": {
        "quadrantInfoPattern": {
          "value": "Currently, the movable point on the circle is in quadrant {{n}} of the coordinate plane."
        },
        "clockwiseAngle": {
          "value": "An angle theta is formed by a clockwise rotation of the point."
        },
        "counterClockwiseAngle": {
          "value": "An angle theta is formed by a counterclockwise rotation of the point."
        },
        "sinFunction": {
          "value": "Sine"
        },
        "cosFunction": {
          "value": "Cosine"
        },
        "tanFunction": {
          "value": "Tangent"
        },
        "valuesDescriptionPattern": {
          "value": "The angle is {{angle}}. For this angle, x equals {{xValue}}; y equals {{yValue}}; {{trigFunction}} equals {{trigValue}}."
        }
      },
      "interactionHint": {
        "value": "Move point on circle or graph to explore different angles."
      }
    }
  }
}

